{
    "name": "sage_intacct",
    "namespace": "fivetran",
    "description": "dbt models for dbt_sage_intacct",
    "latest": "0.1.2",
    "assets": {
        "logo": "logos/placeholder.svg"
    },
    "versions": {
        "0.1.0": {
            "id": "fivetran/sage_intacct/v0.1.0",
            "name": "sage_intacct",
            "version": "0.1.0",
            "published_at": "1970-01-01T00:00:00.000000+00:00",
            "packages": [
                {
                    "package": "fivetran/sage_intacct_source",
                    "version": [
                        ">=0.1.0",
                        "<0.2.0"
                    ]
                }
            ],
            "require_dbt_version": [
                ">=1.0.0",
                "<2.0.0"
            ],
            "works_with": [],
            "downloads": {
                "tarball": "https://raw.githubusercontent.com/ogr003/test-package-hub/main/tarballs/yu-iskw/dbt_unittest/dbt_unittest-0.2.0.tar.gz",
                "format": "tgz",
                "sha1": "584ba11026e260158710bf39cf8efb547dd83fe6"
            }
        },
        "0.1.1": {
            "id": "fivetran/sage_intacct/v0.1.1",
            "name": "sage_intacct",
            "version": "0.1.1",
            "published_at": "1970-01-01T00:00:00.000000+00:00",
            "packages": [
                {
                    "package": "fivetran/sage_intacct_source",
                    "version": [
                        ">=0.1.0",
                        "<0.2.0"
                    ]
                }
            ],
            "require_dbt_version": [
                ">=1.0.0",
                "<2.0.0"
            ],
            "works_with": [],
            "downloads": {
                "tarball": "https://raw.githubusercontent.com/ogr003/test-package-hub/main/tarballs/yu-iskw/dbt_unittest/dbt_unittest-0.2.0.tar.gz",
                "format": "tgz",
                "sha1": "285d03260b754df71da6edcfd1dab836d43dca10"
            }
        },
        "0.1.2": {
            "id": "fivetran/sage_intacct/v0.1.2",
            "name": "sage_intacct",
            "version": "0.1.2",
            "published_at": "1970-01-01T00:00:00.000000+00:00",
            "packages": [
                {
                    "package": "fivetran/sage_intacct_source",
                    "version": [
                        ">=0.1.0",
                        "<0.2.0"
                    ]
                }
            ],
            "require_dbt_version": [
                ">=1.0.0",
                "<2.0.0"
            ],
            "works_with": [],
            "downloads": {
                "tarball": "https://raw.githubusercontent.com/ogr003/test-package-hub/main/tarballs/yu-iskw/dbt_unittest/dbt_unittest-0.2.0.tar.gz",
                "format": "tgz",
                "sha1": "75ef2314c9b332792adf91ff701a9278bdd5b5da"
            }
        }
    }
}